{
  "annotations": {
    "list": [
      {
        "builtIn": 1,
        "datasource": {
          "type": "datasource",
          "uid": "grafana"
        },
        "enable": true,
        "hide": true,
        "iconColor": "rgba(0, 211, 255, 1)",
        "name": "Annotations & Alerts",
        "type": "dashboard"
      }
    ]
  },
  "editable": true,
  "fiscalYearStartMonth": 0,
  "graphTooltip": 0,
  "id": 1,
  "links": [],
  "panels": [
    {
      "datasource": {
        "type": "prometheus",
        "uid": "PBFA97CFB590B2093"
      },
      "fieldConfig": {
        "defaults": {
          "color": {
            "mode": "palette-classic"
          },
          "custom": {
            "axisBorderShow": false,
            "axisCenteredZero": false,
            "axisColorMode": "text",
            "axisLabel": "",
            "axisPlacement": "hidden",
            "barAlignment": 0,
            "barWidthFactor": 0.6,
            "drawStyle": "line",
            "fillOpacity": 0,
            "gradientMode": "none",
            "hideFrom": {
              "legend": false,
              "tooltip": false,
              "viz": false
            },
            "insertNulls": false,
            "lineInterpolation": "linear",
            "lineWidth": 1,
            "pointSize": 5,
            "scaleDistribution": {
              "type": "linear"
            },
            "showPoints": "auto",
            "spanNulls": false,
            "stacking": {
              "group": "A",
              "mode": "none"
            },
            "thresholdsStyle": {
              "mode": "off"
            }
          },
          "decimals": 1,
          "mappings": [
            {
              "options": {
                "match": "null",
                "result": {
                  "text": "N/A"
                }
              },
              "type": "special"
            }
          ],
          "thresholds": {
            "mode": "absolute",
            "steps": [
              {
                "color": "green",
                "value": null
              },
              {
                "color": "red",
                "value": 80
              }
            ]
          },
          "unit": "dtdurations"
        },
        "overrides": []
      },
      "gridPos": {
        "h": 7,
        "w": 6,
        "x": 0,
        "y": 0
      },
      "id": 16,
      "maxDataPoints": 100,
      "options": {
        "legend": {
          "calcs": [],
          "displayMode": "list",
          "placement": "bottom",
          "showLegend": true
        },
        "tooltip": {
          "mode": "single",
          "sort": "none"
        }
      },
      "pluginVersion": "11.3.1",
      "targets": [
        {
          "datasource": {
            "type": "prometheus",
            "uid": "PBFA97CFB590B2093"
          },
          "disableTextWrap": false,
          "editorMode": "code",
          "expr": "process_uptime_seconds{instance=\"$node\"}",
          "fullMetaSearch": false,
          "includeNullMetadata": true,
          "intervalFactor": 2,
          "legendFormat": "",
          "range": true,
          "refId": "A",
          "step": 4,
          "useBackend": false
        }
      ],
      "title": "Uptime",
      "type": "timeseries"
    },
    {
      "datasource": {
        "type": "prometheus",
        "uid": "PBFA97CFB590B2093"
      },
      "fieldConfig": {
        "defaults": {
          "color": {
            "mode": "palette-classic"
          },
          "custom": {
            "axisBorderShow": false,
            "axisCenteredZero": false,
            "axisColorMode": "text",
            "axisLabel": "",
            "axisPlacement": "auto",
            "barAlignment": 0,
            "barWidthFactor": 0.6,
            "drawStyle": "line",
            "fillOpacity": 10,
            "gradientMode": "none",
            "hideFrom": {
              "legend": false,
              "tooltip": false,
              "viz": false
            },
            "insertNulls": false,
            "lineInterpolation": "linear",
            "lineWidth": 1,
            "pointSize": 5,
            "scaleDistribution": {
              "type": "linear"
            },
            "showPoints": "never",
            "spanNulls": false,
            "stacking": {
              "group": "A",
              "mode": "none"
            },
            "thresholdsStyle": {
              "mode": "off"
            }
          },
          "mappings": [],
          "thresholds": {
            "mode": "absolute",
            "steps": [
              {
                "color": "green",
                "value": null
              },
              {
                "color": "red",
                "value": 80
              }
            ]
          },
          "unit": "short"
        },
        "overrides": [
          {
            "matcher": {
              "id": "byName",
              "options": "Reductions"
            },
            "properties": [
              {
                "id": "custom.axisPlacement",
                "value": "right"
              }
            ]
          }
        ]
      },
      "gridPos": {
        "h": 7,
        "w": 8,
        "x": 6,
        "y": 0
      },
      "id": 15,
      "options": {
        "legend": {
          "calcs": [],
          "displayMode": "list",
          "placement": "bottom",
          "showLegend": true
        },
        "tooltip": {
          "mode": "multi",
          "sort": "none"
        }
      },
      "pluginVersion": "11.3.1",
      "targets": [
        {
          "datasource": {
            "type": "prometheus",
            "uid": "PBFA97CFB590B2093"
          },
          "expr": "irate(erlang_vm_statistics_context_switches{instance=\"$node\"}[$interval])",
          "format": "time_series",
          "intervalFactor": 2,
          "legendFormat": "Context Switches",
          "refId": "B",
          "step": 2
        },
        {
          "datasource": {
            "type": "prometheus",
            "uid": "PBFA97CFB590B2093"
          },
          "expr": "irate(erlang_vm_statistics_reductions_total{instance=\"$node\"}[$interval])",
          "format": "time_series",
          "intervalFactor": 2,
          "legendFormat": "Reductions",
          "refId": "C",
          "step": 2
        },
        {
          "datasource": {
            "type": "prometheus",
            "uid": "PBFA97CFB590B2093"
          },
          "editorMode": "code",
          "expr": "irate(erlang_vm_statistics_runtime_milliseconds{instance=\"$node\"}[$interval])",
          "format": "time_series",
          "intervalFactor": 2,
          "legendFormat": "Runtime",
          "range": true,
          "refId": "D",
          "step": 2
        },
        {
          "datasource": {
            "type": "prometheus",
            "uid": "PBFA97CFB590B2093"
          },
          "editorMode": "code",
          "expr": "system_load{instance=\"$node\"}/256",
          "hide": false,
          "instant": false,
          "legendFormat": "Load average (5)",
          "range": true,
          "refId": "E"
        }
      ],
      "title": "Load",
      "type": "timeseries"
    },
    {
      "datasource": {
        "type": "prometheus",
        "uid": "PBFA97CFB590B2093"
      },
      "fieldConfig": {
        "defaults": {
          "color": {
            "mode": "palette-classic"
          },
          "custom": {
            "axisBorderShow": false,
            "axisCenteredZero": false,
            "axisColorMode": "text",
            "axisLabel": "",
            "axisPlacement": "auto",
            "barAlignment": 0,
            "barWidthFactor": 0.6,
            "drawStyle": "line",
            "fillOpacity": 10,
            "gradientMode": "none",
            "hideFrom": {
              "legend": false,
              "tooltip": false,
              "viz": false
            },
            "insertNulls": false,
            "lineInterpolation": "linear",
            "lineWidth": 1,
            "pointSize": 5,
            "scaleDistribution": {
              "type": "linear"
            },
            "showPoints": "never",
            "spanNulls": false,
            "stacking": {
              "group": "A",
              "mode": "none"
            },
            "thresholdsStyle": {
              "mode": "off"
            }
          },
          "mappings": [],
          "thresholds": {
            "mode": "absolute",
            "steps": [
              {
                "color": "green",
                "value": null
              },
              {
                "color": "red",
                "value": 80
              }
            ]
          },
          "unit": "short"
        },
        "overrides": []
      },
      "gridPos": {
        "h": 7,
        "w": 9,
        "x": 14,
        "y": 0
      },
      "id": 14,
      "options": {
        "legend": {
          "calcs": [],
          "displayMode": "list",
          "placement": "bottom",
          "showLegend": true
        },
        "tooltip": {
          "mode": "multi",
          "sort": "none"
        }
      },
      "pluginVersion": "11.3.1",
      "targets": [
        {
          "datasource": {
            "type": "prometheus",
            "uid": "PBFA97CFB590B2093"
          },
          "expr": "erlang_vm_process_limit{instance=\"$node\"}",
          "format": "time_series",
          "hide": true,
          "intervalFactor": 2,
          "legendFormat": "Process Limit",
          "refId": "A",
          "step": 2
        },
        {
          "datasource": {
            "type": "prometheus",
            "uid": "PBFA97CFB590B2093"
          },
          "expr": "erlang_vm_process_count{instance=\"$node\"}",
          "format": "time_series",
          "intervalFactor": 2,
          "legendFormat": "Processes",
          "refId": "B",
          "step": 2
        },
        {
          "datasource": {
            "type": "prometheus",
            "uid": "PBFA97CFB590B2093"
          },
          "expr": "erlang_vm_statistics_run_queues_length_total{instance=\"$node\"}",
          "format": "time_series",
          "intervalFactor": 2,
          "legendFormat": "Run Queues Length",
          "refId": "C",
          "step": 2
        }
      ],
      "title": "Processes",
      "type": "timeseries"
    },
    {
      "datasource": {
        "type": "prometheus",
        "uid": "PBFA97CFB590B2093"
      },
      "fieldConfig": {
        "defaults": {
          "color": {
            "mode": "palette-classic"
          },
          "custom": {
            "axisBorderShow": false,
            "axisCenteredZero": false,
            "axisColorMode": "text",
            "axisLabel": "",
            "axisPlacement": "auto",
            "barAlignment": 0,
            "barWidthFactor": 0.6,
            "drawStyle": "line",
            "fillOpacity": 0,
            "gradientMode": "none",
            "hideFrom": {
              "legend": false,
              "tooltip": false,
              "viz": false
            },
            "insertNulls": false,
            "lineInterpolation": "linear",
            "lineWidth": 1,
            "pointSize": 5,
            "scaleDistribution": {
              "type": "linear"
            },
            "showPoints": "auto",
            "spanNulls": false,
            "stacking": {
              "group": "A",
              "mode": "none"
            },
            "thresholdsStyle": {
              "mode": "off"
            }
          },
          "mappings": [],
          "thresholds": {
            "mode": "absolute",
            "steps": [
              {
                "color": "green",
                "value": null
              },
              {
                "color": "red",
                "value": 80
              }
            ]
          },
          "unit": "bytes"
        },
        "overrides": []
      },
      "gridPos": {
        "h": 7,
        "w": 12,
        "x": 0,
        "y": 7
      },
      "id": 3,
      "options": {
        "legend": {
          "calcs": [],
          "displayMode": "list",
          "placement": "bottom",
          "showLegend": true
        },
        "tooltip": {
          "mode": "single",
          "sort": "none"
        }
      },
      "pluginVersion": "11.3.1",
      "targets": [
        {
          "datasource": {
            "type": "prometheus",
            "uid": "PBFA97CFB590B2093"
          },
          "editorMode": "code",
          "expr": "erlang_vm_memory_bytes_total{instance=\"$node\", kind=\"system\"}",
          "format": "time_series",
          "intervalFactor": 2,
          "legendFormat": "System memory",
          "range": true,
          "refId": "B",
          "step": 2
        },
        {
          "datasource": {
            "type": "prometheus",
            "uid": "PBFA97CFB590B2093"
          },
          "expr": "erlang_vm_memory_system_bytes_total{instance=\"$node\", usage=\"atom\"}",
          "format": "time_series",
          "intervalFactor": 2,
          "legendFormat": "Atoms",
          "refId": "C",
          "step": 2
        },
        {
          "datasource": {
            "type": "prometheus",
            "uid": "PBFA97CFB590B2093"
          },
          "expr": "erlang_vm_memory_system_bytes_total{instance=\"$node\", usage=\"binary\"}",
          "format": "time_series",
          "intervalFactor": 2,
          "legendFormat": "Binary",
          "refId": "D",
          "step": 2
        },
        {
          "datasource": {
            "type": "prometheus",
            "uid": "PBFA97CFB590B2093"
          },
          "expr": "erlang_vm_memory_system_bytes_total{instance=\"$node\", usage=\"code\"}",
          "format": "time_series",
          "intervalFactor": 2,
          "legendFormat": "Code",
          "refId": "E",
          "step": 2
        },
        {
          "datasource": {
            "type": "prometheus",
            "uid": "PBFA97CFB590B2093"
          },
          "editorMode": "code",
          "expr": "erlang_vm_memory_system_bytes_total{instance=\"$node\", usage=\"ets\"}",
          "format": "time_series",
          "intervalFactor": 2,
          "legendFormat": "ETS",
          "range": true,
          "refId": "F",
          "step": 2
        },
        {
          "datasource": {
            "type": "prometheus",
            "uid": "PBFA97CFB590B2093"
          },
          "editorMode": "code",
          "expr": "",
          "hide": false,
          "instant": false,
          "legendFormat": "__auto",
          "range": true,
          "refId": "G"
        }
      ],
      "title": "VM Memory",
      "type": "timeseries"
    },
    {
      "datasource": {
        "type": "prometheus",
        "uid": "PBFA97CFB590B2093"
      },
      "fieldConfig": {
        "defaults": {
          "color": {
            "mode": "palette-classic"
          },
          "custom": {
            "hideFrom": {
              "legend": false,
              "tooltip": false,
              "viz": false
            }
          },
          "mappings": [],
          "unit": "decbytes"
        },
        "overrides": []
      },
      "gridPos": {
        "h": 7,
        "w": 11,
        "x": 12,
        "y": 7
      },
      "id": 19,
      "options": {
        "legend": {
          "displayMode": "list",
          "placement": "right",
          "showLegend": true,
          "values": [
            "value"
          ]
        },
        "pieType": "pie",
        "reduceOptions": {
          "calcs": [
            "lastNotNull"
          ],
          "fields": "",
          "values": false
        },
        "tooltip": {
          "mode": "single",
          "sort": "none"
        }
      },
      "pluginVersion": "11.3.1",
      "targets": [
        {
          "editorMode": "code",
          "expr": "sum(erlang_vm_allocators{usage=\"carriers_size\", instance=~\"$node\"}) by (alloc)",
          "legendFormat": "__auto",
          "range": true,
          "refId": "A"
        }
      ],
      "title": "Memory breakdown",
      "type": "piechart"
    },
    {
      "datasource": {
        "type": "prometheus",
        "uid": "PBFA97CFB590B2093"
      },
      "fieldConfig": {
        "defaults": {
          "color": {
            "mode": "palette-classic"
          },
          "custom": {
            "axisBorderShow": false,
            "axisCenteredZero": false,
            "axisColorMode": "text",
            "axisLabel": "",
            "axisPlacement": "auto",
            "barAlignment": 0,
            "barWidthFactor": 0.6,
            "drawStyle": "line",
            "fillOpacity": 0,
            "gradientMode": "none",
            "hideFrom": {
              "legend": false,
              "tooltip": false,
              "viz": false
            },
            "insertNulls": false,
            "lineInterpolation": "linear",
            "lineWidth": 1,
            "pointSize": 5,
            "scaleDistribution": {
              "type": "linear"
            },
            "showPoints": "auto",
            "spanNulls": false,
            "stacking": {
              "group": "A",
              "mode": "none"
            },
            "thresholdsStyle": {
              "mode": "off"
            }
          },
          "mappings": [],
          "thresholds": {
            "mode": "absolute",
            "steps": [
              {
                "color": "green",
                "value": null
              },
              {
                "color": "red",
                "value": 80
              }
            ]
          }
        },
        "overrides": []
      },
      "gridPos": {
        "h": 8,
        "w": 12,
        "x": 0,
        "y": 14
      },
      "id": 18,
      "options": {
        "legend": {
          "calcs": [],
          "displayMode": "list",
          "placement": "bottom",
          "showLegend": true
        },
        "tooltip": {
          "mode": "single",
          "sort": "none"
        }
      },
      "pluginVersion": "11.3.1",
      "targets": [
        {
          "editorMode": "code",
          "expr": "avg by (method) (rate(cowboy_request_duration_seconds_sum[5m]))",
          "legendFormat": "__auto",
          "range": true,
          "refId": "A"
        }
      ],
      "title": "Average request duration (seconds)",
      "type": "timeseries"
    },
    {
      "datasource": {
        "type": "prometheus",
        "uid": "PBFA97CFB590B2093"
      },
      "fieldConfig": {
        "defaults": {
          "color": {
            "mode": "palette-classic"
          },
          "custom": {
            "axisBorderShow": false,
            "axisCenteredZero": false,
            "axisColorMode": "text",
            "axisLabel": "",
            "axisPlacement": "auto",
            "fillOpacity": 80,
            "gradientMode": "none",
            "hideFrom": {
              "legend": false,
              "tooltip": false,
              "viz": false
            },
            "lineWidth": 1,
            "scaleDistribution": {
              "type": "linear"
            },
            "thresholdsStyle": {
              "mode": "off"
            }
          },
          "mappings": [],
          "thresholds": {
            "mode": "absolute",
            "steps": [
              {
                "color": "green",
                "value": null
              },
              {
                "color": "red",
                "value": 80
              }
            ]
          }
        },
        "overrides": []
      },
      "gridPos": {
        "h": 8,
        "w": 11,
        "x": 12,
        "y": 14
      },
      "id": 17,
      "options": {
        "barRadius": 0,
        "barWidth": 0.97,
        "fullHighlight": false,
        "groupWidth": 0.7,
        "legend": {
          "calcs": [],
          "displayMode": "list",
          "placement": "bottom",
          "showLegend": true
        },
        "orientation": "auto",
        "showValue": "auto",
        "stacking": "normal",
        "tooltip": {
          "mode": "single",
          "sort": "none"
        },
        "xTickLabelRotation": 0,
        "xTickLabelSpacing": 100
      },
      "pluginVersion": "11.3.1",
      "targets": [
        {
          "editorMode": "code",
          "expr": "sum by (method, status_class) (rate(cowboy_requests_total[5m])) * 60\n",
          "legendFormat": "__auto",
          "range": true,
          "refId": "A"
        }
      ],
      "title": "Requests rates (per minute)",
      "type": "barchart"
    },
    {
      "datasource": {
        "type": "prometheus",
        "uid": "PBFA97CFB590B2093"
      },
      "fieldConfig": {
        "defaults": {
          "color": {
            "mode": "palette-classic"
          },
          "custom": {
            "axisBorderShow": false,
            "axisCenteredZero": false,
            "axisColorMode": "text",
            "axisLabel": "",
            "axisPlacement": "auto",
            "barAlignment": 0,
            "barWidthFactor": 0.6,
            "drawStyle": "line",
            "fillOpacity": 10,
            "gradientMode": "none",
            "hideFrom": {
              "legend": false,
              "tooltip": false,
              "viz": false
            },
            "insertNulls": false,
            "lineInterpolation": "linear",
            "lineWidth": 2,
            "pointSize": 5,
            "scaleDistribution": {
              "type": "linear"
            },
            "showPoints": "never",
            "spanNulls": true,
            "stacking": {
              "group": "A",
              "mode": "none"
            },
            "thresholdsStyle": {
              "mode": "off"
            }
          },
          "mappings": [],
          "thresholds": {
            "mode": "absolute",
            "steps": [
              {
                "color": "green",
                "value": null
              },
              {
                "color": "red",
                "value": 80
              }
            ]
          },
          "unit": "decbytes"
        },
        "overrides": []
      },
      "gridPos": {
        "h": 6,
        "w": 12,
        "x": 0,
        "y": 22
      },
      "id": 6,
      "options": {
        "legend": {
          "calcs": [],
          "displayMode": "list",
          "placement": "bottom",
          "showLegend": true
        },
        "tooltip": {
          "mode": "multi",
          "sort": "none"
        }
      },
      "pluginVersion": "11.3.1",
      "targets": [
        {
          "datasource": {
            "type": "prometheus",
            "uid": "PBFA97CFB590B2093"
          },
          "expr": "irate(erlang_vm_statistics_bytes_output_total{instance=\"$node\"}[$interval])",
          "format": "time_series",
          "intervalFactor": 2,
          "legendFormat": "Output Bytes",
          "metric": "erlang_vm_statistics_bytes_output_total",
          "refId": "A",
          "step": 2
        },
        {
          "datasource": {
            "type": "prometheus",
            "uid": "PBFA97CFB590B2093"
          },
          "expr": "irate(erlang_vm_statistics_bytes_received_total{instance=\"$node\"}[$interval])",
          "format": "time_series",
          "intervalFactor": 2,
          "legendFormat": "Received Bytes",
          "metric": "erlang_vm_statistics_bytes_received_total",
          "refId": "B",
          "step": 2
        }
      ],
      "title": "VM IO",
      "type": "timeseries"
    },
    {
      "datasource": {
        "type": "prometheus",
        "uid": "PBFA97CFB590B2093"
      },
      "fieldConfig": {
        "defaults": {
          "color": {
            "mode": "palette-classic"
          },
          "custom": {
            "axisBorderShow": false,
            "axisCenteredZero": false,
            "axisColorMode": "text",
            "axisLabel": "",
            "axisPlacement": "auto",
            "barAlignment": 0,
            "barWidthFactor": 0.6,
            "drawStyle": "line",
            "fillOpacity": 10,
            "gradientMode": "none",
            "hideFrom": {
              "legend": false,
              "tooltip": false,
              "viz": false
            },
            "insertNulls": false,
            "lineInterpolation": "linear",
            "lineWidth": 2,
            "pointSize": 5,
            "scaleDistribution": {
              "type": "linear"
            },
            "showPoints": "never",
            "spanNulls": true,
            "stacking": {
              "group": "A",
              "mode": "none"
            },
            "thresholdsStyle": {
              "mode": "off"
            }
          },
          "mappings": [],
          "thresholds": {
            "mode": "absolute",
            "steps": [
              {
                "color": "green",
                "value": null
              },
              {
                "color": "red",
                "value": 80
              }
            ]
          },
          "unit": "short"
        },
        "overrides": [
          {
            "matcher": {
              "id": "byName",
              "options": "Words Reclaimed"
            },
            "properties": [
              {
                "id": "unit",
                "value": "decbytes"
              },
              {
                "id": "custom.axisPlacement",
                "value": "right"
              }
            ]
          },
          {
            "matcher": {
              "id": "byName",
              "options": "Bytes Reclaimed"
            },
            "properties": [
              {
                "id": "unit",
                "value": "decbytes"
              },
              {
                "id": "custom.axisPlacement",
                "value": "right"
              }
            ]
          }
        ]
      },
      "gridPos": {
        "h": 6,
        "w": 11,
        "x": 12,
        "y": 22
      },
      "id": 7,
      "options": {
        "legend": {
          "calcs": [],
          "displayMode": "list",
          "placement": "bottom",
          "showLegend": true
        },
        "tooltip": {
          "mode": "multi",
          "sort": "none"
        }
      },
      "pluginVersion": "11.3.1",
      "targets": [
        {
          "datasource": {
            "type": "prometheus",
            "uid": "PBFA97CFB590B2093"
          },
          "expr": "irate(erlang_vm_statistics_garbage_collection_number_of_gcs{instance=\"$node\"}[$interval])",
          "format": "time_series",
          "intervalFactor": 2,
          "legendFormat": "Number of GCs",
          "metric": "erlang_vm_statistics_garbage_collection_number_of_gcs",
          "refId": "A",
          "step": 2
        },
        {
          "datasource": {
            "type": "prometheus",
            "uid": "PBFA97CFB590B2093"
          },
          "expr": "irate(erlang_vm_statistics_garbage_collection_bytes_reclaimed{instance=\"$node\"}[$interval])",
          "format": "time_series",
          "intervalFactor": 2,
          "legendFormat": "Bytes Reclaimed",
          "metric": "erlang_vm_statistics_garbage_collection_words_reclaimed",
          "refId": "B",
          "step": 2
        }
      ],
      "title": "VM GC",
      "type": "timeseries"
    },
    {
      "datasource": {
        "type": "prometheus",
        "uid": "PBFA97CFB590B2093"
      },
      "fieldConfig": {
        "defaults": {
          "color": {
            "mode": "palette-classic"
          },
          "custom": {
            "axisBorderShow": false,
            "axisCenteredZero": false,
            "axisColorMode": "text",
            "axisLabel": "",
            "axisPlacement": "auto",
            "barAlignment": 0,
            "barWidthFactor": 0.6,
            "drawStyle": "line",
            "fillOpacity": 10,
            "gradientMode": "none",
            "hideFrom": {
              "legend": false,
              "tooltip": false,
              "viz": false
            },
            "insertNulls": false,
            "lineInterpolation": "linear",
            "lineWidth": 2,
            "pointSize": 5,
            "scaleDistribution": {
              "type": "linear"
            },
            "showPoints": "never",
            "spanNulls": true,
            "stacking": {
              "group": "A",
              "mode": "none"
            },
            "thresholdsStyle": {
              "mode": "off"
            }
          },
          "mappings": [],
          "thresholds": {
            "mode": "absolute",
            "steps": [
              {
                "color": "green",
                "value": null
              },
              {
                "color": "red",
                "value": 80
              }
            ]
          },
          "unit": "none"
        },
        "overrides": [
          {
            "matcher": {
              "id": "byName",
              "options": "Max Ports"
            },
            "properties": [
              {
                "id": "unit",
                "value": "short"
              },
              {
                "id": "custom.axisPlacement",
                "value": "right"
              }
            ]
          },
          {
            "matcher": {
              "id": "byName",
              "options": "Ports"
            },
            "properties": [
              {
                "id": "unit",
                "value": "short"
              },
              {
                "id": "custom.axisPlacement",
                "value": "right"
              }
            ]
          }
        ]
      },
      "gridPos": {
        "h": 7,
        "w": 8,
        "x": 8,
        "y": 28
      },
      "id": 8,
      "options": {
        "legend": {
          "calcs": [],
          "displayMode": "list",
          "placement": "bottom",
          "showLegend": true
        },
        "tooltip": {
          "mode": "multi",
          "sort": "none"
        }
      },
      "pluginVersion": "11.3.1",
      "targets": [
        {
          "datasource": {
            "type": "prometheus",
            "uid": "PBFA97CFB590B2093"
          },
          "expr": "process_open_fds{instance=\"$node\"}",
          "format": "time_series",
          "intervalFactor": 2,
          "legendFormat": "Open FDs",
          "metric": "",
          "refId": "A",
          "step": 2
        },
        {
          "datasource": {
            "type": "prometheus",
            "uid": "PBFA97CFB590B2093"
          },
          "expr": "process_max_fds{instance=\"$node\"}",
          "format": "time_series",
          "intervalFactor": 2,
          "legendFormat": "Max FDs",
          "refId": "B",
          "step": 2
        },
        {
          "datasource": {
            "type": "prometheus",
            "uid": "PBFA97CFB590B2093"
          },
          "expr": "erlang_vm_port_limit{instance=\"$node\"}",
          "format": "time_series",
          "intervalFactor": 2,
          "legendFormat": "Max Ports",
          "refId": "C",
          "step": 2
        },
        {
          "datasource": {
            "type": "prometheus",
            "uid": "PBFA97CFB590B2093"
          },
          "expr": "erlang_vm_port_count{instance=\"$node\"}",
          "format": "time_series",
          "intervalFactor": 2,
          "legendFormat": "Ports",
          "refId": "D",
          "step": 2
        }
      ],
      "title": "File Descriptors & Ports",
      "type": "timeseries"
    }
  ],
  "preload": false,
  "refresh": "5s",
  "schemaVersion": 40,
  "tags": [],
  "templating": {
    "list": [
      {
        "current": {
          "text": "172.17.0.1:4000",
          "value": "172.17.0.1:4000"
        },
        "datasource": "Prometheus",
        "includeAll": false,
        "label": "Node",
        "name": "node",
        "options": [],
        "query": "label_values(erlang_vm_process_count, instance)",
        "refresh": 1,
        "regex": "",
        "sort": 1,
        "type": "query"
      },
      {
        "auto": false,
        "auto_count": 30,
        "auto_min": "10s",
        "current": {
          "text": "5m",
          "value": "5m"
        },
        "name": "interval",
        "options": [
          {
            "selected": false,
            "text": "1m",
            "value": "1m"
          },
          {
            "selected": true,
            "text": "5m",
            "value": "5m"
          },
          {
            "selected": false,
            "text": "10m",
            "value": "10m"
          },
          {
            "selected": false,
            "text": "30m",
            "value": "30m"
          },
          {
            "selected": false,
            "text": "1h",
            "value": "1h"
          },
          {
            "selected": false,
            "text": "6h",
            "value": "6h"
          },
          {
            "selected": false,
            "text": "12h",
            "value": "12h"
          },
          {
            "selected": false,
            "text": "1d",
            "value": "1d"
          },
          {
            "selected": false,
            "text": "7d",
            "value": "7d"
          },
          {
            "selected": false,
            "text": "14d",
            "value": "14d"
          },
          {
            "selected": false,
            "text": "30d",
            "value": "30d"
          }
        ],
        "query": "1m,5m,10m,30m,1h,6h,12h,1d,7d,14d,30d",
        "refresh": 2,
        "type": "interval"
      }
    ]
  },
  "time": {
    "from": "now-5m",
    "to": "now"
  },
  "timepicker": {},
  "timezone": "browser",
  "title": "BEAM",
  "uid": "ce50mecnfs4cga",
  "version": 7,
  "weekStart": ""
}
